latex_input/__main__.py
latex_input/cached_unicode_data.py
latex_input/input_client_linux.py
latex_input/input_client_win.py
latex_input/latex_converter.py
latex_input/listener.py
latex_input/parse_unicode_data.py
latex_input/unicode_data.py
latex_input/unicode_structs.py
latex_input/data/icon.ico
latex_input/data/icon_activated.ico
latex_input-0.3.1.dist-info/LICENSE
latex_input-0.3.1.dist-info/METADATA
latex_input-0.3.1.dist-info/WHEEL
latex_input-0.3.1.dist-info/top_level.txt
latex_input-0.3.1.dist-info/RECORD
