Metadata-Version: 2.1
Name: latex-input
Version: 0.3.1
Summary: Use LaTeX-style inputs to write the equivalent unicode characters anywhere
Author-email: kmgb <kevinmgb@proton.me>
Project-URL: Homepage, https://github.com/kmgb/latex_input
Project-URL: Bug Tracker, https://github.com/kmgb/latex_input/issues
Classifier: Programming Language :: Python :: 3
Classifier: License :: OSI Approved :: GNU General Public License v3 (GPLv3)
Requires-Python: >=3.10
License-File: LICENSE
Requires-Dist: PyQt6
Requires-Dist: ahk
Requires-Dist: ahk-binary
Requires-Dist: pynput
Requires-Dist: keyboard (==0.13.5)
